ttq/__init__.py
ttq/option.py
ttq/parser.py
ttq/question.py
ttq/quiz.py
ttq/type.py
ttq-1.0.0.dist-info/LICENSE
ttq-1.0.0.dist-info/METADATA
ttq-1.0.0.dist-info/WHEEL
ttq-1.0.0.dist-info/top_level.txt
ttq-1.0.0.dist-info/RECORD
