Metadata-Version: 2.1
Name: ttq
Version: 1.0.0
Summary: Formatlangan matndan testlarni yaratish
Home-page: https://github.com/djumanov/ttq
Author: Diyorbek Jumanov
Author-email: djumanovdev@email.com
License: UNKNOWN
Platform: UNKNOWN
Classifier: Programming Language :: Python :: 3
Classifier: License :: OSI Approved :: MIT License
Classifier: Operating System :: OS Independent
Requires-Python: >=3.6
License-File: LICENSE
